lto/__init__.py
lto/binary.py
lto/crypto.py
lto/ethereum_mnemonic_utils.py
lto/public_node.py
lto/transaction.py
lto/word_list.py
lto/accounts/__init__.py
lto/accounts/account.py
lto/accounts/account_factory.py
lto/accounts/brainwallet.py
lto/accounts/ecdsa/__init__.py
lto/accounts/ecdsa/account_ecdsa.py
lto/accounts/ecdsa/account_factory_ecdsa.py
lto/accounts/ed25519/__init__.py
lto/accounts/ed25519/account_ed25519.py
lto/accounts/ed25519/account_factory_ed25519.py
lto/transactions/__init__.py
lto/transactions/anchor.py
lto/transactions/association.py
lto/transactions/burn.py
lto/transactions/cancel_lease.py
lto/transactions/cancel_sponsorship.py
lto/transactions/certificate.py
lto/transactions/data.py
lto/transactions/data_entry.py
lto/transactions/lease.py
lto/transactions/mapped_anchor.py
lto/transactions/mass_transfer.py
lto/transactions/register.py
lto/transactions/revoke_association.py
lto/transactions/set_script.py
lto/transactions/sponsorship.py
lto/transactions/statement.py
lto/transactions/transfer.py
lto-1.5.1.dist-info/licenses/LICENSE
lto-1.5.1.dist-info/METADATA
lto-1.5.1.dist-info/WHEEL
lto-1.5.1.dist-info/top_level.txt
lto-1.5.1.dist-info/RECORD
