Metadata-Version: 2.4
Name: lto
Version: 1.5.1
Summary: LTO Network Python API
Home-page: https://github.com/ltonetwork/lto-api.python
Author: LTO Network
Author-email: info@ltonetwork.com
Project-URL: Bug Tracker, https://github.com/ltonetwork/lto-api.python/issues
Classifier: Programming Language :: Python :: 3
Classifier: License :: OSI Approved :: MIT License
Classifier: Operating System :: OS Independent
Requires-Python: >=3.8
License-File: LICENSE
Requires-Dist: requests<3,>=2.24.0
Requires-Dist: PyNaCl
Requires-Dist: base58~=0.2.5
Requires-Dist: ecdsa~=0.17.0
Requires-Dist: inflection~=0.5.1
Requires-Dist: freezegun~=1.1.0
Requires-Dist: mnemonic~=0.20
Requires-Dist: eth-utils~=2.0.0
Requires-Dist: pycryptodome~=3.12.0
Requires-Dist: bip32~=4.0.0
Requires-Dist: cryptography<43,>=42.0.0
Dynamic: license-file
